fsynth/__init__.py
fsynth/cli.py
fsynth/engine.py
fsynth/fundamentals.py
fsynth-0.1.1.dist-info/licenses/LICENSE.txt
fsynth-0.1.1.dist-info/METADATA
fsynth-0.1.1.dist-info/WHEEL
fsynth-0.1.1.dist-info/entry_points.txt
fsynth-0.1.1.dist-info/top_level.txt
fsynth-0.1.1.dist-info/RECORD
