Metadata-Version: 2.4
Name: fsynth
Version: 0.1.1
Summary: A high-performance synthetic financial data generator that uses Heston Stochastic Volatility and Jump Diffusion models.
Author-email: Arnav Malhotra <am@welcra.com>
Project-URL: Homepage, https://github.com/welcra/fsynth
Project-URL: Bug Tracker, https://github.com/welcra/fsynth/issues
Classifier: Development Status :: 4 - Beta
Classifier: Intended Audience :: Financial and Insurance Industry
Classifier: Intended Audience :: Science/Research
Classifier: Topic :: Office/Business :: Financial :: Investment
Classifier: Topic :: Scientific/Engineering :: Mathematics
Classifier: License :: OSI Approved :: MIT License
Classifier: Programming Language :: Python :: 3
Requires-Python: >=3.9
License-File: LICENSE.txt
Requires-Dist: numpy>=1.20.0
Requires-Dist: pandas>=1.5.0
Requires-Dist: numba>=0.56.0
Requires-Dist: pyarrow>=10.0.0
Dynamic: license-file
